pyqt_bounding_box/__init__.py
pyqt_bounding_box/boundingBox.py
pyqt_bounding_box-0.0.14.dist-info/LICENSE
pyqt_bounding_box-0.0.14.dist-info/METADATA
pyqt_bounding_box-0.0.14.dist-info/WHEEL
pyqt_bounding_box-0.0.14.dist-info/top_level.txt
pyqt_bounding_box-0.0.14.dist-info/RECORD
