Metadata-Version: 2.1
Name: pyqt-bounding-box
Version: 0.0.14
Summary: PyQt bounding box for graphic design software
Home-page: https://github.com/yjg30737/pyqt-bounding-box.git
Author: Jung Gyu Yoon
Author-email: yjg30737@gmail.com
License: MIT
License-File: LICENSE
Requires-Dist: PyQt5 (>=5.8)
